{
  "evaluation": {
    "games": 16,
    "wins": 15,
    "win_rate": 0.9375,
    "avg_vp": 6.812500011175871,
    "seed": 50200000,
    "planner_seed": 50200000,
    "victory_target": 7,
    "visibility": "realistic",
    "candidate_net": "training/runs/20260612-2244-h2-policy-head-continuation-5m/screening/base.ctnn",
    "late_policy_net": "training/runs/20260613-alpha-counterfactual-independent-v5/counterfactual.ctnn",
    "late_policy_min_vp": 5,
    "final_policy_net": null,
    "final_policy_min_vp": 6,
    "final_policy_min_cities": 0,
    "opponent_net": "models/catan-512.ctnn",
    "opponent": "alpha",
    "root_k": 8,
    "samples": 96,
    "depth": 300,
    "planner": "hybrid-v2",
    "continuation_decisions": 1,
    "value_weight": 1.0,
    "potential_weight": 0.25,
    "opponent_root_k": 1,
    "opponent_samples": 1,
    "opponent_depth": 0,
    "settlement_neural_mix": 0.0,
    "strategy_settlement_weight": 1.0,
    "opening_production_weight": 5.0,
    "opening_city_weight": 0.0,
    "opening_city_seat_mask": 15,
    "opening_settlement_lookahead": true,
    "opening_rollout_candidates": 12,
    "opening_rollout_samples": 32,
    "opening_rollout_finalists": 3,
    "opening_rollout_final_samples": 128,
    "opening_rollout_prior_weight": 0.04,
    "rollout_vp_margin_weight": 0.0,
    "common_rollout_random_numbers": true,
    "search_common_random_numbers": false,
    "independent_rollout_seeds": true,
    "second_settlement_rollout_samples": 0,
    "heuristic_refinement": true,
    "endgame_conversion": true,
    "immediate_vp_min": 0,
    "conversion_min_vp": 5,
    "proposal_conversion_min_vp": 5,
    "conversion_saving_min_vp": 8,
    "conversion_saving_max_deficit": 0,
    "endgame_road_push": false,
    "opening_road_planning": false,
    "road_refinement": true,
    "road_length_weight": 5.0,
    "road_settlement_weight": 20.0,
    "knight_pressure": true,
    "leader_robber_weight": 1.0,
    "blocking_settlement_weight": 0.0,
    "trade_refinement": false,
    "resource_tactics": true,
    "end_turn_trade_sweep": false,
    "evolved_state_refinement": false,
    "state_refinement_mix": 0.0,
    "hybrid_search_root_k": 1,
    "hybrid_search_samples": 1,
    "hybrid_search_continuation": 0,
    "hybrid_search_value_weight": 1.0,
    "hybrid_search_potential_weight": 0.0,
    "hybrid_search_vp_gain_weight": 0.0,
    "hybrid_search_building_gain_weight": 0.0,
    "hybrid_search_road_control_weight": 0.0,
    "hybrid_search_min_vp": 0,
    "hybrid_search_max_hidden_vp": 5,
    "hybrid_search_to_terminal": false,
    "hybrid_search_max_decisions": 64,
    "search_opening_decisions": -1
  },
  "summary": {
    "wins": {
      "games": 15,
      "win_rate": 1.0,
      "candidate_vp": 7.0,
      "vp_margin": 2.8,
      "turns": 41.4667,
      "opening_income": {
        "wheat": 0.163,
        "sheep": 0.1352,
        "wood": 0.0944,
        "brick": 0.063,
        "stone": 0.1481
      },
      "opening_total_income": 0.6037,
      "opening_best_strategy": 0.0667,
      "candidate_cities": 1.3333,
      "candidate_settlements": 1.6667,
      "candidate_road_length": 3.8667,
      "candidate_knights": 2.3333,
      "longest_road_rate": 0.1333,
      "largest_army_rate": 0.6,
      "hidden_vp": 1.2,
      "action_mix": {
        "settlement": 3.0,
        "city": 1.3333,
        "road": 4.2667,
        "robber": 4.2667,
        "steal": 3.3333,
        "discard": 2.7333,
        "monopoly": 0.2667,
        "year_of_plenty": 0.2,
        "bank_trade": 1.5333,
        "propose_trade": 25.3333,
        "respond_trade": 0.0,
        "confirm_trade": 10.7333,
        "roll": 0.5333,
        "buy_dev": 4.9333,
        "knight": 2.3333,
        "road_building": 0.3333,
        "end_turn": 5.0
      }
    },
    "losses": {
      "games": 1,
      "win_rate": 0.0,
      "candidate_vp": 4.0,
      "vp_margin": -3.0,
      "turns": 69.0,
      "opening_income": {
        "wheat": 0.1389,
        "sheep": 0.3611,
        "wood": 0.0556,
        "brick": 0.0833,
        "stone": 0.0
      },
      "opening_total_income": 0.6389,
      "opening_best_strategy": 0.0278,
      "candidate_cities": 0.0,
      "candidate_settlements": 3.0,
      "candidate_road_length": 6.0,
      "candidate_knights": 5.0,
      "longest_road_rate": 0.0,
      "largest_army_rate": 0.0,
      "hidden_vp": 1.0,
      "action_mix": {
        "settlement": 3.0,
        "city": 0.0,
        "road": 6.0,
        "robber": 6.0,
        "steal": 6.0,
        "discard": 0.0,
        "monopoly": 1.0,
        "year_of_plenty": 1.0,
        "bank_trade": 1.0,
        "propose_trade": 45.0,
        "respond_trade": 0.0,
        "confirm_trade": 25.0,
        "roll": 0.0,
        "buy_dev": 10.0,
        "knight": 5.0,
        "road_building": 1.0,
        "end_turn": 5.0
      }
    },
    "by_seat": {
      "0": {
        "games": 4,
        "win_rate": 1.0,
        "candidate_vp": 7.0,
        "vp_margin": 2.75,
        "turns": 35.0,
        "opening_income": {
          "wheat": 0.1875,
          "sheep": 0.1319,
          "wood": 0.0972,
          "brick": 0.0833,
          "stone": 0.125
        },
        "opening_total_income": 0.625,
        "opening_best_strategy": 0.0903,
        "candidate_cities": 1.75,
        "candidate_settlements": 1.25,
        "candidate_road_length": 4.0,
        "candidate_knights": 2.0,
        "longest_road_rate": 0.25,
        "largest_army_rate": 0.5,
        "hidden_vp": 0.75,
        "action_mix": {
          "settlement": 3.0,
          "city": 1.75,
          "road": 5.0,
          "robber": 3.75,
          "steal": 3.25,
          "discard": 1.0,
          "monopoly": 0.0,
          "year_of_plenty": 0.5,
          "bank_trade": 1.25,
          "propose_trade": 22.0,
          "respond_trade": 0.0,
          "confirm_trade": 5.75,
          "roll": 0.25,
          "buy_dev": 3.5,
          "knight": 2.0,
          "road_building": 0.0,
          "end_turn": 4.25
        }
      },
      "1": {
        "games": 4,
        "win_rate": 1.0,
        "candidate_vp": 7.0,
        "vp_margin": 3.0,
        "turns": 43.0,
        "opening_income": {
          "wheat": 0.1667,
          "sheep": 0.1597,
          "wood": 0.0833,
          "brick": 0.0347,
          "stone": 0.1528
        },
        "opening_total_income": 0.5972,
        "opening_best_strategy": 0.0556,
        "candidate_cities": 1.0,
        "candidate_settlements": 1.25,
        "candidate_road_length": 3.25,
        "candidate_knights": 3.5,
        "longest_road_rate": 0.0,
        "largest_army_rate": 1.0,
        "hidden_vp": 1.75,
        "action_mix": {
          "settlement": 2.25,
          "city": 1.0,
          "road": 3.25,
          "robber": 4.5,
          "steal": 3.25,
          "discard": 1.0,
          "monopoly": 0.5,
          "year_of_plenty": 0.25,
          "bank_trade": 0.75,
          "propose_trade": 26.75,
          "respond_trade": 0.0,
          "confirm_trade": 13.75,
          "roll": 0.25,
          "buy_dev": 7.25,
          "knight": 3.5,
          "road_building": 0.5,
          "end_turn": 5.25
        }
      },
      "2": {
        "games": 4,
        "win_rate": 0.75,
        "candidate_vp": 6.25,
        "vp_margin": 1.5,
        "turns": 53.75,
        "opening_income": {
          "wheat": 0.1181,
          "sheep": 0.1806,
          "wood": 0.0972,
          "brick": 0.1042,
          "stone": 0.1389
        },
        "opening_total_income": 0.6389,
        "opening_best_strategy": 0.0278,
        "candidate_cities": 0.75,
        "candidate_settlements": 3.0,
        "candidate_road_length": 4.5,
        "candidate_knights": 2.5,
        "longest_road_rate": 0.0,
        "largest_army_rate": 0.25,
        "hidden_vp": 1.25,
        "action_mix": {
          "settlement": 3.75,
          "city": 0.75,
          "road": 5.0,
          "robber": 5.25,
          "steal": 4.75,
          "discard": 6.25,
          "monopoly": 0.25,
          "year_of_plenty": 0.25,
          "bank_trade": 3.0,
          "propose_trade": 36.0,
          "respond_trade": 0.0,
          "confirm_trade": 15.75,
          "roll": 0.0,
          "buy_dev": 5.5,
          "knight": 2.5,
          "road_building": 0.5,
          "end_turn": 5.0
        }
      },
      "3": {
        "games": 4,
        "win_rate": 1.0,
        "candidate_vp": 7.0,
        "vp_margin": 2.5,
        "turns": 41.0,
        "opening_income": {
          "wheat": 0.1736,
          "sheep": 0.125,
          "wood": 0.0903,
          "brick": 0.0347,
          "stone": 0.1389
        },
        "opening_total_income": 0.5625,
        "opening_best_strategy": 0.0833,
        "candidate_cities": 1.5,
        "candidate_settlements": 1.5,
        "candidate_road_length": 4.25,
        "candidate_knights": 2.0,
        "longest_road_rate": 0.25,
        "largest_army_rate": 0.5,
        "hidden_vp": 1.0,
        "action_mix": {
          "settlement": 3.0,
          "city": 1.5,
          "road": 4.25,
          "robber": 4.0,
          "steal": 2.75,
          "discard": 2.0,
          "monopoly": 0.5,
          "year_of_plenty": 0.0,
          "bank_trade": 1.0,
          "propose_trade": 21.5,
          "respond_trade": 0.0,
          "confirm_trade": 11.25,
          "roll": 1.5,
          "buy_dev": 4.75,
          "knight": 2.0,
          "road_building": 0.5,
          "end_turn": 5.5
        }
      }
    },
    "loss_vp_distribution": {
      "4": 1
    },
    "loss_winner_awards": {
      "longest_road": 1.0,
      "largest_army": 0.0
    }
  },
  "games": [
    {
      "game": 0,
      "board_seed": 50200000,
      "candidate_seat": 0,
      "winner": 0,
      "won": true,
      "turns": 24,
      "vp_margin": 4.0,
      "opening": {
        "vertices": [
          24,
          18
        ],
        "income": [
          0.194444,
          0.194444,
          0.055556,
          0.0,
          0.138889
        ],
        "income_by_resource": {
          "wheat": 0.194444,
          "sheep": 0.194444,
          "wood": 0.055556,
          "brick": 0.0,
          "stone": 0.138889
        },
        "resource_diversity": 4,
        "strategy": {
          "expansion": 0.0,
          "city": 0.046296,
          "development": 0.138889,
          "best": 0.138889
        }
      },
      "candidate_actions": {
        "settlement": 2,
        "road": 2,
        "propose_trade": 11,
        "confirm_trade": 7,
        "buy_dev": 7,
        "end_turn": 3,
        "knight": 3,
        "robber": 6,
        "steal": 5,
        "year_of_plenty": 2,
        "city": 2,
        "roll": 1
      },
      "candidate": {
        "vp": 7.0,
        "public_vp": 6,
        "hidden_vp": 1.0,
        "building_vp": 4,
        "award_vp": 2,
        "cards": 1,
        "dev_cards_held": 2,
        "knights_played": 3,
        "settlements": 0,
        "cities": 2,
        "roads": 2,
        "road_length": 2,
        "longest_road": false,
        "largest_army": true,
        "port_3_to_1": false,
        "ports_2_to_1": []
      },
      "winner_metrics": {
        "vp": 7.0,
        "public_vp": 6,
        "hidden_vp": 1.0,
        "building_vp": 4,
        "award_vp": 2,
        "cards": 1,
        "dev_cards_held": 2,
        "knights_played": 3,
        "settlements": 0,
        "cities": 2,
        "roads": 2,
        "road_length": 2,
        "longest_road": false,
        "largest_army": true,
        "port_3_to_1": false,
        "ports_2_to_1": []
      },
      "players": [
        {
          "vp": 7.0,
          "public_vp": 6,
          "hidden_vp": 1.0,
          "building_vp": 4,
          "award_vp": 2,
          "cards": 1,
          "dev_cards_held": 2,
          "knights_played": 3,
          "settlements": 0,
          "cities": 2,
          "roads": 2,
          "road_length": 2,
          "longest_road": false,
          "largest_army": true,
          "port_3_to_1": false,
          "ports_2_to_1": []
        },
        {
          "vp": 2.0,
          "public_vp": 2,
          "hidden_vp": 0.0,
          "building_vp": 2,
          "award_vp": 0,
          "cards": 5,
          "dev_cards_held": 0,
          "knights_played": 0,
          "settlements": 2,
          "cities": 0,
          "roads": 4,
          "road_length": 4,
          "longest_road": false,
          "largest_army": false,
          "port_3_to_1": false,
          "ports_2_to_1": []
        },
        {
          "vp": 3.0,
          "public_vp": 3,
          "hidden_vp": 0.0,
          "building_vp": 3,
          "award_vp": 0,
          "cards": 0,
          "dev_cards_held": 0,
          "knights_played": 0,
          "settlements": 3,
          "cities": 0,
          "roads": 3,
          "road_length": 3,
          "longest_road": false,
          "largest_army": false,
          "port_3_to_1": true,
          "ports_2_to_1": []
        },
        {
          "vp": 2.0,
          "public_vp": 2,
          "hidden_vp": 0.0,
          "building_vp": 2,
          "award_vp": 0,
          "cards": 1,
          "dev_cards_held": 1,
          "knights_played": 1,
          "settlements": 2,
          "cities": 0,
          "roads": 5,
          "road_length": 4,
          "longest_road": false,
          "largest_army": false,
          "port_3_to_1": false,
          "ports_2_to_1": []
        }
      ]
    },
    {
      "game": 1,
      "board_seed": 50200000,
      "candidate_seat": 1,
      "winner": 1,
      "won": true,
      "turns": 33,
      "vp_margin": 4.0,
      "opening": {
        "vertices": [
          24,
          18
        ],
        "income": [
          0.194444,
          0.194444,
          0.055556,
          0.0,
          0.138889
        ],
        "income_by_resource": {
          "wheat": 0.194444,
          "sheep": 0.194444,
          "wood": 0.055556,
          "brick": 0.0,
          "stone": 0.138889
        },
        "resource_diversity": 4,
        "strategy": {
          "expansion": 0.0,
          "city": 0.046296,
          "development": 0.138889,
          "best": 0.138889
        }
      },
      "candidate_actions": {
        "settlement": 2,
        "road": 4,
        "buy_dev": 11,
        "propose_trade": 18,
        "confirm_trade": 5,
        "end_turn": 4,
        "road_building": 1,
        "year_of_plenty": 1,
        "monopoly": 1,
        "bank_trade": 1,
        "knight": 4,
        "robber": 5,
        "steal": 4
      },
      "candidate": {
        "vp": 7.0,
        "public_vp": 4,
        "hidden_vp": 3.0,
        "building_vp": 2,
        "award_vp": 2,
        "cards": 5,
        "dev_cards_held": 4,
        "knights_played": 4,
        "settlements": 2,
        "cities": 0,
        "roads": 4,
        "road_length": 4,
        "longest_road": false,
        "largest_army": true,
        "port_3_to_1": false,
        "ports_2_to_1": []
      },
      "winner_metrics": {
        "vp": 7.0,
        "public_vp": 4,
        "hidden_vp": 3.0,
        "building_vp": 2,
        "award_vp": 2,
        "cards": 5,
        "dev_cards_held": 4,
        "knights_played": 4,
        "settlements": 2,
        "cities": 0,
        "roads": 4,
        "road_length": 4,
        "longest_road": false,
        "largest_army": true,
        "port_3_to_1": false,
        "ports_2_to_1": []
      },
      "players": [
        {
          "vp": 2.0,
          "public_vp": 2,
          "hidden_vp": 0.0,
          "building_vp": 2,
          "award_vp": 0,
          "cards": 7,
          "dev_cards_held": 0,
          "knights_played": 0,
          "settlements": 2,
          "cities": 0,
          "roads": 5,
          "road_length": 3,
          "longest_road": false,
          "largest_army": false,
          "port_3_to_1": false,
          "ports_2_to_1": []
        },
        {
          "vp": 7.0,
          "public_vp": 4,
          "hidden_vp": 3.0,
          "building_vp": 2,
          "award_vp": 2,
          "cards": 5,
          "dev_cards_held": 4,
          "knights_played": 4,
          "settlements": 2,
          "cities": 0,
          "roads": 4,
          "road_length": 4,
          "longest_road": false,
          "largest_army": true,
          "port_3_to_1": false,
          "ports_2_to_1": []
        },
        {
          "vp": 2.0,
          "public_vp": 2,
          "hidden_vp": 0.0,
          "building_vp": 2,
          "award_vp": 0,
          "cards": 10,
          "dev_cards_held": 0,
          "knights_played": 1,
          "settlements": 2,
          "cities": 0,
          "roads": 2,
          "road_length": 2,
          "longest_road": false,
          "largest_army": false,
          "port_3_to_1": false,
          "ports_2_to_1": []
        },
        {
          "vp": 3.0,
          "public_vp": 3,
          "hidden_vp": 0.0,
          "building_vp": 3,
          "award_vp": 0,
          "cards": 5,
          "dev_cards_held": 0,
          "knights_played": 3,
          "settlements": 3,
          "cities": 0,
          "roads": 3,
          "road_length": 3,
          "longest_road": false,
          "largest_army": false,
          "port_3_to_1": false,
          "ports_2_to_1": [
            "wood"
          ]
        }
      ]
    },
    {
      "game": 2,
      "board_seed": 50200000,
      "candidate_seat": 2,
      "winner": 1,
      "won": false,
      "turns": 69,
      "vp_margin": -3.0,
      "opening": {
        "vertices": [
          30,
          19
        ],
        "income": [
          0.138889,
          0.361111,
          0.055556,
          0.083333,
          0.0
        ],
        "income_by_resource": {
          "wheat": 0.138889,
          "sheep": 0.361111,
          "wood": 0.055556,
          "brick": 0.083333,
          "stone": 0.0
        },
        "resource_diversity": 4,
        "strategy": {
          "expansion": 0.027778,
          "city": 0.0,
          "development": 0.0,
          "best": 0.027778
        }
      },
      "candidate_actions": {
        "settlement": 3,
        "road": 6,
        "propose_trade": 45,
        "confirm_trade": 25,
        "buy_dev": 10,
        "end_turn": 5,
        "road_building": 1,
        "knight": 5,
        "robber": 6,
        "steal": 6,
        "monopoly": 1,
        "year_of_plenty": 1,
        "bank_trade": 1
      },
      "candidate": {
        "vp": 4.0,
        "public_vp": 3,
        "hidden_vp": 1.0,
        "building_vp": 3,
        "award_vp": 0,
        "cards": 9,
        "dev_cards_held": 2,
        "knights_played": 5,
        "settlements": 3,
        "cities": 0,
        "roads": 6,
        "road_length": 6,
        "longest_road": false,
        "largest_army": false,
        "port_3_to_1": false,
        "ports_2_to_1": []
      },
      "winner_metrics": {
        "vp": 7.0,
        "public_vp": 4,
        "hidden_vp": 3.0,
        "building_vp": 2,
        "award_vp": 2,
        "cards": 3,
        "dev_cards_held": 3,
        "knights_played": 1,
        "settlements": 2,
        "cities": 0,
        "roads": 8,
        "road_length": 8,
        "longest_road": true,
        "largest_army": false,
        "port_3_to_1": false,
        "ports_2_to_1": []
      },
      "players": [
        {
          "vp": 5.0,
          "public_vp": 4,
          "hidden_vp": 1.0,
          "building_vp": 2,
          "award_vp": 2,
          "cards": 6,
          "dev_cards_held": 1,
          "knights_played": 7,
          "settlements": 2,
          "cities": 0,
          "roads": 5,
          "road_length": 3,
          "longest_road": false,
          "largest_army": true,
          "port_3_to_1": false,
          "ports_2_to_1": []
        },
        {
          "vp": 7.0,
          "public_vp": 4,
          "hidden_vp": 3.0,
          "building_vp": 2,
          "award_vp": 2,
          "cards": 3,
          "dev_cards_held": 3,
          "knights_played": 1,
          "settlements": 2,
          "cities": 0,
          "roads": 8,
          "road_length": 8,
          "longest_road": true,
          "largest_army": false,
          "port_3_to_1": false,
          "ports_2_to_1": []
        },
        {
          "vp": 4.0,
          "public_vp": 3,
          "hidden_vp": 1.0,
          "building_vp": 3,
          "award_vp": 0,
          "cards": 9,
          "dev_cards_held": 2,
          "knights_played": 5,
          "settlements": 3,
          "cities": 0,
          "roads": 6,
          "road_length": 6,
          "longest_road": false,
          "largest_army": false,
          "port_3_to_1": false,
          "ports_2_to_1": []
        },
        {
          "vp": 3.0,
          "public_vp": 3,
          "hidden_vp": 0.0,
          "building_vp": 3,
          "award_vp": 0,
          "cards": 2,
          "dev_cards_held": 1,
          "knights_played": 0,
          "settlements": 1,
          "cities": 1,
          "roads": 5,
          "road_length": 3,
          "longest_road": false,
          "largest_army": false,
          "port_3_to_1": false,
          "ports_2_to_1": []
        }
      ]
    },
    {
      "game": 3,
      "board_seed": 50200000,
      "candidate_seat": 3,
      "winner": 3,
      "won": true,
      "turns": 35,
      "vp_margin": 3.0,
      "opening": {
        "vertices": [
          8,
          24
        ],
        "income": [
          0.194444,
          0.055556,
          0.027778,
          0.0,
          0.25
        ],
        "income_by_resource": {
          "wheat": 0.194444,
          "sheep": 0.055556,
          "wood": 0.027778,
          "brick": 0.0,
          "stone": 0.25
        },
        "resource_diversity": 4,
        "strategy": {
          "expansion": 0.0,
          "city": 0.083333,
          "development": 0.055556,
          "best": 0.083333
        }
      },
      "candidate_actions": {
        "settlement": 3,
        "road": 3,
        "city": 3,
        "end_turn": 5,
        "propose_trade": 14,
        "robber": 4,
        "steal": 4,
        "buy_dev": 4,
        "confirm_trade": 5,
        "knight": 2,
        "bank_trade": 1
      },
      "candidate": {
        "vp": 7.0,
        "public_vp": 6,
        "hidden_vp": 1.0,
        "building_vp": 6,
        "award_vp": 0,
        "cards": 0,
        "dev_cards_held": 2,
        "knights_played": 2,
        "settlements": 0,
        "cities": 3,
        "roads": 3,
        "road_length": 3,
        "longest_road": false,
        "largest_army": false,
        "port_3_to_1": false,
        "ports_2_to_1": []
      },
      "winner_metrics": {
        "vp": 7.0,
        "public_vp": 6,
        "hidden_vp": 1.0,
        "building_vp": 6,
        "award_vp": 0,
        "cards": 0,
        "dev_cards_held": 2,
        "knights_played": 2,
        "settlements": 0,
        "cities": 3,
        "roads": 3,
        "road_length": 3,
        "longest_road": false,
        "largest_army": false,
        "port_3_to_1": false,
        "ports_2_to_1": []
      },
      "players": [
        {
          "vp": 4.0,
          "public_vp": 4,
          "hidden_vp": 0.0,
          "building_vp": 2,
          "award_vp": 2,
          "cards": 6,
          "dev_cards_held": 1,
          "knights_played": 3,
          "settlements": 2,
          "cities": 0,
          "roads": 3,
          "road_length": 3,
          "longest_road": false,
          "largest_army": true,
          "port_3_to_1": false,
          "ports_2_to_1": []
        },
        {
          "vp": 2.0,
          "public_vp": 2,
          "hidden_vp": 0.0,
          "building_vp": 2,
          "award_vp": 0,
          "cards": 2,
          "dev_cards_held": 1,
          "knights_played": 0,
          "settlements": 2,
          "cities": 0,
          "roads": 3,
          "road_length": 3,
          "longest_road": false,
          "largest_army": false,
          "port_3_to_1": false,
          "ports_2_to_1": []
        },
        {
          "vp": 2.0,
          "public_vp": 2,
          "hidden_vp": 0.0,
          "building_vp": 2,
          "award_vp": 0,
          "cards": 8,
          "dev_cards_held": 0,
          "knights_played": 0,
          "settlements": 2,
          "cities": 0,
          "roads": 6,
          "road_length": 4,
          "longest_road": false,
          "largest_army": false,
          "port_3_to_1": false,
          "ports_2_to_1": []
        },
        {
          "vp": 7.0,
          "public_vp": 6,
          "hidden_vp": 1.0,
          "building_vp": 6,
          "award_vp": 0,
          "cards": 0,
          "dev_cards_held": 2,
          "knights_played": 2,
          "settlements": 0,
          "cities": 3,
          "roads": 3,
          "road_length": 3,
          "longest_road": false,
          "largest_army": false,
          "port_3_to_1": false,
          "ports_2_to_1": []
        }
      ]
    },
    {
      "game": 4,
      "board_seed": 50200001,
      "candidate_seat": 0,
      "winner": 0,
      "won": true,
      "turns": 44,
      "vp_margin": 1.0,
      "opening": {
        "vertices": [
          13,
          38
        ],
        "income": [
          0.138889,
          0.111111,
          0.111111,
          0.111111,
          0.083333
        ],
        "income_by_resource": {
          "wheat": 0.138889,
          "sheep": 0.111111,
          "wood": 0.111111,
          "brick": 0.111111,
          "stone": 0.083333
        },
        "resource_diversity": 5,
        "strategy": {
          "expansion": 0.055556,
          "city": 0.027778,
          "development": 0.083333,
          "best": 0.083333
        }
      },
      "candidate_actions": {
        "settlement": 5,
        "road": 10,
        "robber": 3,
        "steal": 3,
        "propose_trade": 33,
        "confirm_trade": 9,
        "buy_dev": 1,
        "knight": 1,
        "end_turn": 3,
        "city": 2
      },
      "candidate": {
        "vp": 7.0,
        "public_vp": 7,
        "hidden_vp": 0.0,
        "building_vp": 7,
        "award_vp": 0,
        "cards": 7,
        "dev_cards_held": 0,
        "knights_played": 1,
        "settlements": 3,
        "cities": 2,
        "roads": 10,
        "road_length": 6,
        "longest_road": false,
        "largest_army": false,
        "port_3_to_1": false,
        "ports_2_to_1": [
          "wheat"
        ]
      },
      "winner_metrics": {
        "vp": 7.0,
        "public_vp": 7,
        "hidden_vp": 0.0,
        "building_vp": 7,
        "award_vp": 0,
        "cards": 7,
        "dev_cards_held": 0,
        "knights_played": 1,
        "settlements": 3,
        "cities": 2,
        "roads": 10,
        "road_length": 6,
        "longest_road": false,
        "largest_army": false,
        "port_3_to_1": false,
        "ports_2_to_1": [
          "wheat"
        ]
      },
      "players": [
        {
          "vp": 7.0,
          "public_vp": 7,
          "hidden_vp": 0.0,
          "building_vp": 7,
          "award_vp": 0,
          "cards": 7,
          "dev_cards_held": 0,
          "knights_played": 1,
          "settlements": 3,
          "cities": 2,
          "roads": 10,
          "road_length": 6,
          "longest_road": false,
          "largest_army": false,
          "port_3_to_1": false,
          "ports_2_to_1": [
            "wheat"
          ]
        },
        {
          "vp": 4.0,
          "public_vp": 4,
          "hidden_vp": 0.0,
          "building_vp": 2,
          "award_vp": 2,
          "cards": 2,
          "dev_cards_held": 0,
          "knights_played": 0,
          "settlements": 2,
          "cities": 0,
          "roads": 11,
          "road_length": 6,
          "longest_road": true,
          "largest_army": false,
          "port_3_to_1": false,
          "ports_2_to_1": [
            "sheep"
          ]
        },
        {
          "vp": 6.0,
          "public_vp": 4,
          "hidden_vp": 2.0,
          "building_vp": 2,
          "award_vp": 2,
          "cards": 3,
          "dev_cards_held": 2,
          "knights_played": 3,
          "settlements": 2,
          "cities": 0,
          "roads": 3,
          "road_length": 3,
          "longest_road": false,
          "largest_army": true,
          "port_3_to_1": false,
          "ports_2_to_1": []
        },
        {
          "vp": 2.0,
          "public_vp": 2,
          "hidden_vp": 0.0,
          "building_vp": 2,
          "award_vp": 0,
          "cards": 5,
          "dev_cards_held": 0,
          "knights_played": 0,
          "settlements": 2,
          "cities": 0,
          "roads": 6,
          "road_length": 3,
          "longest_road": false,
          "largest_army": false,
          "port_3_to_1": false,
          "ports_2_to_1": []
        }
      ]
    },
    {
      "game": 5,
      "board_seed": 50200001,
      "candidate_seat": 1,
      "winner": 1,
      "won": true,
      "turns": 57,
      "vp_margin": 3.0,
      "opening": {
        "vertices": [
          14,
          43
        ],
        "income": [
          0.138889,
          0.277778,
          0.083333,
          0.0,
          0.083333
        ],
        "income_by_resource": {
          "wheat": 0.138889,
          "sheep": 0.277778,
          "wood": 0.083333,
          "brick": 0.0,
          "stone": 0.083333
        },
        "resource_diversity": 4,
        "strategy": {
          "expansion": 0.0,
          "city": 0.027778,
          "development": 0.083333,
          "best": 0.083333
        }
      },
      "candidate_actions": {
        "settlement": 2,
        "road": 4,
        "propose_trade": 27,
        "confirm_trade": 14,
        "buy_dev": 8,
        "knight": 4,
        "robber": 5,
        "steal": 4,
        "end_turn": 7,
        "road_building": 1,
        "monopoly": 1,
        "city": 2,
        "roll": 1,
        "bank_trade": 1
      },
      "candidate": {
        "vp": 7.0,
        "public_vp": 6,
        "hidden_vp": 1.0,
        "building_vp": 4,
        "award_vp": 2,
        "cards": 5,
        "dev_cards_held": 2,
        "knights_played": 4,
        "settlements": 0,
        "cities": 2,
        "roads": 4,
        "road_length": 4,
        "longest_road": false,
        "largest_army": true,
        "port_3_to_1": false,
        "ports_2_to_1": []
      },
      "winner_metrics": {
        "vp": 7.0,
        "public_vp": 6,
        "hidden_vp": 1.0,
        "building_vp": 4,
        "award_vp": 2,
        "cards": 5,
        "dev_cards_held": 2,
        "knights_played": 4,
        "settlements": 0,
        "cities": 2,
        "roads": 4,
        "road_length": 4,
        "longest_road": false,
        "largest_army": true,
        "port_3_to_1": false,
        "ports_2_to_1": []
      },
      "players": [
        {
          "vp": 3.0,
          "public_vp": 3,
          "hidden_vp": 0.0,
          "building_vp": 3,
          "award_vp": 0,
          "cards": 4,
          "dev_cards_held": 0,
          "knights_played": 0,
          "settlements": 3,
          "cities": 0,
          "roads": 11,
          "road_length": 5,
          "longest_road": false,
          "largest_army": false,
          "port_3_to_1": false,
          "ports_2_to_1": [
            "stone"
          ]
        },
        {
          "vp": 7.0,
          "public_vp": 6,
          "hidden_vp": 1.0,
          "building_vp": 4,
          "award_vp": 2,
          "cards": 5,
          "dev_cards_held": 2,
          "knights_played": 4,
          "settlements": 0,
          "cities": 2,
          "roads": 4,
          "road_length": 4,
          "longest_road": false,
          "largest_army": true,
          "port_3_to_1": false,
          "ports_2_to_1": []
        },
        {
          "vp": 3.0,
          "public_vp": 2,
          "hidden_vp": 1.0,
          "building_vp": 2,
          "award_vp": 0,
          "cards": 5,
          "dev_cards_held": 1,
          "knights_played": 0,
          "settlements": 2,
          "cities": 0,
          "roads": 4,
          "road_length": 4,
          "longest_road": false,
          "largest_army": false,
          "port_3_to_1": false,
          "ports_2_to_1": []
        },
        {
          "vp": 4.0,
          "public_vp": 4,
          "hidden_vp": 0.0,
          "building_vp": 2,
          "award_vp": 2,
          "cards": 6,
          "dev_cards_held": 0,
          "knights_played": 0,
          "settlements": 2,
          "cities": 0,
          "roads": 11,
          "road_length": 8,
          "longest_road": true,
          "largest_army": false,
          "port_3_to_1": false,
          "ports_2_to_1": []
        }
      ]
    },
    {
      "game": 6,
      "board_seed": 50200001,
      "candidate_seat": 2,
      "winner": 2,
      "won": true,
      "turns": 38,
      "vp_margin": 4.0,
      "opening": {
        "vertices": [
          9,
          3
        ],
        "income": [
          0.0,
          0.277778,
          0.111111,
          0.111111,
          0.111111
        ],
        "income_by_resource": {
          "wheat": 0.0,
          "sheep": 0.277778,
          "wood": 0.111111,
          "brick": 0.111111,
          "stone": 0.111111
        },
        "resource_diversity": 4,
        "strategy": {
          "expansion": 0.0,
          "city": 0.0,
          "development": 0.0,
          "best": 0.0
        }
      },
      "candidate_actions": {
        "settlement": 4,
        "road": 4,
        "propose_trade": 24,
        "confirm_trade": 10,
        "buy_dev": 6,
        "knight": 3,
        "robber": 5,
        "steal": 4,
        "end_turn": 4,
        "bank_trade": 2,
        "discard": 4
      },
      "candidate": {
        "vp": 7.0,
        "public_vp": 6,
        "hidden_vp": 1.0,
        "building_vp": 4,
        "award_vp": 2,
        "cards": 2,
        "dev_cards_held": 3,
        "knights_played": 3,
        "settlements": 4,
        "cities": 0,
        "roads": 4,
        "road_length": 4,
        "longest_road": false,
        "largest_army": true,
        "port_3_to_1": false,
        "ports_2_to_1": [
          "brick"
        ]
      },
      "winner_metrics": {
        "vp": 7.0,
        "public_vp": 6,
        "hidden_vp": 1.0,
        "building_vp": 4,
        "award_vp": 2,
        "cards": 2,
        "dev_cards_held": 3,
        "knights_played": 3,
        "settlements": 4,
        "cities": 0,
        "roads": 4,
        "road_length": 4,
        "longest_road": false,
        "largest_army": true,
        "port_3_to_1": false,
        "ports_2_to_1": [
          "brick"
        ]
      },
      "players": [
        {
          "vp": 3.0,
          "public_vp": 3,
          "hidden_vp": 0.0,
          "building_vp": 3,
          "award_vp": 0,
          "cards": 7,
          "dev_cards_held": 0,
          "knights_played": 0,
          "settlements": 1,
          "cities": 1,
          "roads": 4,
          "road_length": 4,
          "longest_road": false,
          "largest_army": false,
          "port_3_to_1": false,
          "ports_2_to_1": []
        },
        {
          "vp": 2.0,
          "public_vp": 2,
          "hidden_vp": 0.0,
          "building_vp": 2,
          "award_vp": 0,
          "cards": 3,
          "dev_cards_held": 0,
          "knights_played": 0,
          "settlements": 2,
          "cities": 0,
          "roads": 4,
          "road_length": 4,
          "longest_road": false,
          "largest_army": false,
          "port_3_to_1": false,
          "ports_2_to_1": []
        },
        {
          "vp": 7.0,
          "public_vp": 6,
          "hidden_vp": 1.0,
          "building_vp": 4,
          "award_vp": 2,
          "cards": 2,
          "dev_cards_held": 3,
          "knights_played": 3,
          "settlements": 4,
          "cities": 0,
          "roads": 4,
          "road_length": 4,
          "longest_road": false,
          "largest_army": true,
          "port_3_to_1": false,
          "ports_2_to_1": [
            "brick"
          ]
        },
        {
          "vp": 2.0,
          "public_vp": 2,
          "hidden_vp": 0.0,
          "building_vp": 2,
          "award_vp": 0,
          "cards": 6,
          "dev_cards_held": 0,
          "knights_played": 1,
          "settlements": 2,
          "cities": 0,
          "roads": 4,
          "road_length": 4,
          "longest_road": false,
          "largest_army": false,
          "port_3_to_1": false,
          "ports_2_to_1": []
        }
      ]
    },
    {
      "game": 7,
      "board_seed": 50200001,
      "candidate_seat": 3,
      "winner": 3,
      "won": true,
      "turns": 55,
      "vp_margin": 1.0,
      "opening": {
        "vertices": [
          46,
          14
        ],
        "income": [
          0.138889,
          0.277778,
          0.055556,
          0.0,
          0.083333
        ],
        "income_by_resource": {
          "wheat": 0.138889,
          "sheep": 0.277778,
          "wood": 0.055556,
          "brick": 0.0,
          "stone": 0.083333
        },
        "resource_diversity": 4,
        "strategy": {
          "expansion": 0.0,
          "city": 0.027778,
          "development": 0.083333,
          "best": 0.083333
        }
      },
      "candidate_actions": {
        "settlement": 2,
        "road": 3,
        "robber": 6,
        "steal": 3,
        "buy_dev": 8,
        "end_turn": 12,
        "knight": 3,
        "propose_trade": 24,
        "confirm_trade": 11,
        "monopoly": 2,
        "discard": 4,
        "roll": 6,
        "bank_trade": 2,
        "city": 1
      },
      "candidate": {
        "vp": 7.0,
        "public_vp": 5,
        "hidden_vp": 2.0,
        "building_vp": 3,
        "award_vp": 2,
        "cards": 0,
        "dev_cards_held": 3,
        "knights_played": 3,
        "settlements": 1,
        "cities": 1,
        "roads": 3,
        "road_length": 3,
        "longest_road": false,
        "largest_army": true,
        "port_3_to_1": true,
        "ports_2_to_1": []
      },
      "winner_metrics": {
        "vp": 7.0,
        "public_vp": 5,
        "hidden_vp": 2.0,
        "building_vp": 3,
        "award_vp": 2,
        "cards": 0,
        "dev_cards_held": 3,
        "knights_played": 3,
        "settlements": 1,
        "cities": 1,
        "roads": 3,
        "road_length": 3,
        "longest_road": false,
        "largest_army": true,
        "port_3_to_1": true,
        "ports_2_to_1": []
      },
      "players": [
        {
          "vp": 6.0,
          "public_vp": 6,
          "hidden_vp": 0.0,
          "building_vp": 4,
          "award_vp": 2,
          "cards": 7,
          "dev_cards_held": 0,
          "knights_played": 0,
          "settlements": 0,
          "cities": 2,
          "roads": 7,
          "road_length": 7,
          "longest_road": true,
          "largest_army": false,
          "port_3_to_1": false,
          "ports_2_to_1": []
        },
        {
          "vp": 2.0,
          "public_vp": 2,
          "hidden_vp": 0.0,
          "building_vp": 2,
          "award_vp": 0,
          "cards": 6,
          "dev_cards_held": 0,
          "knights_played": 0,
          "settlements": 2,
          "cities": 0,
          "roads": 3,
          "road_length": 3,
          "longest_road": false,
          "largest_army": false,
          "port_3_to_1": false,
          "ports_2_to_1": []
        },
        {
          "vp": 2.0,
          "public_vp": 2,
          "hidden_vp": 0.0,
          "building_vp": 2,
          "award_vp": 0,
          "cards": 5,
          "dev_cards_held": 0,
          "knights_played": 0,
          "settlements": 2,
          "cities": 0,
          "roads": 6,
          "road_length": 5,
          "longest_road": false,
          "largest_army": false,
          "port_3_to_1": false,
          "ports_2_to_1": []
        },
        {
          "vp": 7.0,
          "public_vp": 5,
          "hidden_vp": 2.0,
          "building_vp": 3,
          "award_vp": 2,
          "cards": 0,
          "dev_cards_held": 3,
          "knights_played": 3,
          "settlements": 1,
          "cities": 1,
          "roads": 3,
          "road_length": 3,
          "longest_road": false,
          "largest_army": true,
          "port_3_to_1": true,
          "ports_2_to_1": []
        }
      ]
    },
    {
      "game": 8,
      "board_seed": 50200002,
      "candidate_seat": 0,
      "winner": 0,
      "won": true,
      "turns": 44,
      "vp_margin": 2.0,
      "opening": {
        "vertices": [
          41,
          43
        ],
        "income": [
          0.138889,
          0.222222,
          0.0,
          0.0,
          0.277778
        ],
        "income_by_resource": {
          "wheat": 0.138889,
          "sheep": 0.222222,
          "wood": 0.0,
          "brick": 0.0,
          "stone": 0.277778
        },
        "resource_diversity": 3,
        "strategy": {
          "expansion": 0.0,
          "city": 0.069445,
          "development": 0.138889,
          "best": 0.138889
        }
      },
      "candidate_actions": {
        "settlement": 2,
        "road": 3,
        "robber": 6,
        "steal": 5,
        "buy_dev": 5,
        "end_turn": 7,
        "knight": 4,
        "propose_trade": 27,
        "confirm_trade": 2,
        "city": 2,
        "bank_trade": 4
      },
      "candidate": {
        "vp": 7.0,
        "public_vp": 6,
        "hidden_vp": 1.0,
        "building_vp": 4,
        "award_vp": 2,
        "cards": 6,
        "dev_cards_held": 1,
        "knights_played": 4,
        "settlements": 0,
        "cities": 2,
        "roads": 3,
        "road_length": 3,
        "longest_road": false,
        "largest_army": true,
        "port_3_to_1": false,
        "ports_2_to_1": []
      },
      "winner_metrics": {
        "vp": 7.0,
        "public_vp": 6,
        "hidden_vp": 1.0,
        "building_vp": 4,
        "award_vp": 2,
        "cards": 6,
        "dev_cards_held": 1,
        "knights_played": 4,
        "settlements": 0,
        "cities": 2,
        "roads": 3,
        "road_length": 3,
        "longest_road": false,
        "largest_army": true,
        "port_3_to_1": false,
        "ports_2_to_1": []
      },
      "players": [
        {
          "vp": 7.0,
          "public_vp": 6,
          "hidden_vp": 1.0,
          "building_vp": 4,
          "award_vp": 2,
          "cards": 6,
          "dev_cards_held": 1,
          "knights_played": 4,
          "settlements": 0,
          "cities": 2,
          "roads": 3,
          "road_length": 3,
          "longest_road": false,
          "largest_army": true,
          "port_3_to_1": false,
          "ports_2_to_1": []
        },
        {
          "vp": 5.0,
          "public_vp": 4,
          "hidden_vp": 1.0,
          "building_vp": 2,
          "award_vp": 2,
          "cards": 4,
          "dev_cards_held": 2,
          "knights_played": 0,
          "settlements": 2,
          "cities": 0,
          "roads": 5,
          "road_length": 5,
          "longest_road": true,
          "largest_army": false,
          "port_3_to_1": false,
          "ports_2_to_1": []
        },
        {
          "vp": 3.0,
          "public_vp": 3,
          "hidden_vp": 0.0,
          "building_vp": 3,
          "award_vp": 0,
          "cards": 4,
          "dev_cards_held": 0,
          "knights_played": 1,
          "settlements": 1,
          "cities": 1,
          "roads": 2,
          "road_length": 2,
          "longest_road": false,
          "largest_army": false,
          "port_3_to_1": false,
          "ports_2_to_1": []
        },
        {
          "vp": 2.0,
          "public_vp": 2,
          "hidden_vp": 0.0,
          "building_vp": 2,
          "award_vp": 0,
          "cards": 3,
          "dev_cards_held": 1,
          "knights_played": 1,
          "settlements": 2,
          "cities": 0,
          "roads": 6,
          "road_length": 5,
          "longest_road": false,
          "largest_army": false,
          "port_3_to_1": false,
          "ports_2_to_1": []
        }
      ]
    },
    {
      "game": 9,
      "board_seed": 50200002,
      "candidate_seat": 1,
      "winner": 1,
      "won": true,
      "turns": 45,
      "vp_margin": 2.0,
      "opening": {
        "vertices": [
          20,
          31
        ],
        "income": [
          0.0,
          0.083333,
          0.111111,
          0.138889,
          0.388889
        ],
        "income_by_resource": {
          "wheat": 0.0,
          "sheep": 0.083333,
          "wood": 0.111111,
          "brick": 0.138889,
          "stone": 0.388889
        },
        "resource_diversity": 4,
        "strategy": {
          "expansion": 0.0,
          "city": 0.0,
          "development": 0.0,
          "best": 0.0
        }
      },
      "candidate_actions": {
        "settlement": 3,
        "road": 3,
        "propose_trade": 36,
        "confirm_trade": 22,
        "end_turn": 5,
        "buy_dev": 4,
        "knight": 3,
        "robber": 5,
        "steal": 3,
        "discard": 4,
        "bank_trade": 1,
        "city": 1
      },
      "candidate": {
        "vp": 7.0,
        "public_vp": 6,
        "hidden_vp": 1.0,
        "building_vp": 4,
        "award_vp": 2,
        "cards": 1,
        "dev_cards_held": 1,
        "knights_played": 3,
        "settlements": 2,
        "cities": 1,
        "roads": 3,
        "road_length": 3,
        "longest_road": false,
        "largest_army": true,
        "port_3_to_1": false,
        "ports_2_to_1": []
      },
      "winner_metrics": {
        "vp": 7.0,
        "public_vp": 6,
        "hidden_vp": 1.0,
        "building_vp": 4,
        "award_vp": 2,
        "cards": 1,
        "dev_cards_held": 1,
        "knights_played": 3,
        "settlements": 2,
        "cities": 1,
        "roads": 3,
        "road_length": 3,
        "longest_road": false,
        "largest_army": true,
        "port_3_to_1": false,
        "ports_2_to_1": []
      },
      "players": [
        {
          "vp": 3.0,
          "public_vp": 2,
          "hidden_vp": 1.0,
          "building_vp": 2,
          "award_vp": 0,
          "cards": 4,
          "dev_cards_held": 1,
          "knights_played": 1,
          "settlements": 2,
          "cities": 0,
          "roads": 2,
          "road_length": 2,
          "longest_road": false,
          "largest_army": false,
          "port_3_to_1": false,
          "ports_2_to_1": []
        },
        {
          "vp": 7.0,
          "public_vp": 6,
          "hidden_vp": 1.0,
          "building_vp": 4,
          "award_vp": 2,
          "cards": 1,
          "dev_cards_held": 1,
          "knights_played": 3,
          "settlements": 2,
          "cities": 1,
          "roads": 3,
          "road_length": 3,
          "longest_road": false,
          "largest_army": true,
          "port_3_to_1": false,
          "ports_2_to_1": []
        },
        {
          "vp": 5.0,
          "public_vp": 5,
          "hidden_vp": 0.0,
          "building_vp": 3,
          "award_vp": 2,
          "cards": 2,
          "dev_cards_held": 0,
          "knights_played": 2,
          "settlements": 3,
          "cities": 0,
          "roads": 8,
          "road_length": 7,
          "longest_road": true,
          "largest_army": false,
          "port_3_to_1": false,
          "ports_2_to_1": []
        },
        {
          "vp": 2.0,
          "public_vp": 2,
          "hidden_vp": 0.0,
          "building_vp": 2,
          "award_vp": 0,
          "cards": 6,
          "dev_cards_held": 0,
          "knights_played": 0,
          "settlements": 2,
          "cities": 0,
          "roads": 7,
          "road_length": 6,
          "longest_road": false,
          "largest_army": false,
          "port_3_to_1": false,
          "ports_2_to_1": []
        }
      ]
    },
    {
      "game": 10,
      "board_seed": 50200002,
      "candidate_seat": 2,
      "winner": 2,
      "won": true,
      "turns": 70,
      "vp_margin": 3.0,
      "opening": {
        "vertices": [
          24,
          34
        ],
        "income": [
          0.055556,
          0.0,
          0.111111,
          0.0,
          0.444444
        ],
        "income_by_resource": {
          "wheat": 0.055556,
          "sheep": 0.0,
          "wood": 0.111111,
          "brick": 0.0,
          "stone": 0.444444
        },
        "resource_diversity": 3,
        "strategy": {
          "expansion": 0.0,
          "city": 0.027778,
          "development": 0.0,
          "best": 0.027778
        }
      },
      "candidate_actions": {
        "settlement": 3,
        "road": 4,
        "propose_trade": 48,
        "end_turn": 9,
        "confirm_trade": 14,
        "bank_trade": 8,
        "buy_dev": 4,
        "knight": 2,
        "robber": 8,
        "steal": 7,
        "discard": 9,
        "city": 2
      },
      "candidate": {
        "vp": 7.0,
        "public_vp": 5,
        "hidden_vp": 2.0,
        "building_vp": 5,
        "award_vp": 0,
        "cards": 2,
        "dev_cards_held": 2,
        "knights_played": 2,
        "settlements": 1,
        "cities": 2,
        "roads": 4,
        "road_length": 4,
        "longest_road": false,
        "largest_army": false,
        "port_3_to_1": false,
        "ports_2_to_1": []
      },
      "winner_metrics": {
        "vp": 7.0,
        "public_vp": 5,
        "hidden_vp": 2.0,
        "building_vp": 5,
        "award_vp": 0,
        "cards": 2,
        "dev_cards_held": 2,
        "knights_played": 2,
        "settlements": 1,
        "cities": 2,
        "roads": 4,
        "road_length": 4,
        "longest_road": false,
        "largest_army": false,
        "port_3_to_1": false,
        "ports_2_to_1": []
      },
      "players": [
        {
          "vp": 4.0,
          "public_vp": 4,
          "hidden_vp": 0.0,
          "building_vp": 4,
          "award_vp": 0,
          "cards": 5,
          "dev_cards_held": 0,
          "knights_played": 2,
          "settlements": 4,
          "cities": 0,
          "roads": 12,
          "road_length": 5,
          "longest_road": false,
          "largest_army": false,
          "port_3_to_1": true,
          "ports_2_to_1": []
        },
        {
          "vp": 3.0,
          "public_vp": 3,
          "hidden_vp": 0.0,
          "building_vp": 3,
          "award_vp": 0,
          "cards": 3,
          "dev_cards_held": 2,
          "knights_played": 1,
          "settlements": 1,
          "cities": 1,
          "roads": 4,
          "road_length": 4,
          "longest_road": false,
          "largest_army": false,
          "port_3_to_1": false,
          "ports_2_to_1": []
        },
        {
          "vp": 7.0,
          "public_vp": 5,
          "hidden_vp": 2.0,
          "building_vp": 5,
          "award_vp": 0,
          "cards": 2,
          "dev_cards_held": 2,
          "knights_played": 2,
          "settlements": 1,
          "cities": 2,
          "roads": 4,
          "road_length": 4,
          "longest_road": false,
          "largest_army": false,
          "port_3_to_1": false,
          "ports_2_to_1": []
        },
        {
          "vp": 4.0,
          "public_vp": 4,
          "hidden_vp": 0.0,
          "building_vp": 2,
          "award_vp": 2,
          "cards": 5,
          "dev_cards_held": 0,
          "knights_played": 0,
          "settlements": 2,
          "cities": 0,
          "roads": 14,
          "road_length": 8,
          "longest_road": true,
          "largest_army": false,
          "port_3_to_1": false,
          "ports_2_to_1": []
        }
      ]
    },
    {
      "game": 11,
      "board_seed": 50200002,
      "candidate_seat": 3,
      "winner": 3,
      "won": true,
      "turns": 43,
      "vp_margin": 3.0,
      "opening": {
        "vertices": [
          29,
          24
        ],
        "income": [
          0.222222,
          0.083333,
          0.111111,
          0.0,
          0.138889
        ],
        "income_by_resource": {
          "wheat": 0.222222,
          "sheep": 0.083333,
          "wood": 0.111111,
          "brick": 0.0,
          "stone": 0.138889
        },
        "resource_diversity": 4,
        "strategy": {
          "expansion": 0.0,
          "city": 0.046296,
          "development": 0.083333,
          "best": 0.083333
        }
      },
      "candidate_actions": {
        "settlement": 3,
        "road": 3,
        "propose_trade": 27,
        "confirm_trade": 13,
        "city": 1,
        "robber": 6,
        "steal": 4,
        "buy_dev": 5,
        "knight": 3,
        "end_turn": 4,
        "discard": 4,
        "bank_trade": 1
      },
      "candidate": {
        "vp": 7.0,
        "public_vp": 6,
        "hidden_vp": 1.0,
        "building_vp": 4,
        "award_vp": 2,
        "cards": 4,
        "dev_cards_held": 2,
        "knights_played": 3,
        "settlements": 2,
        "cities": 1,
        "roads": 3,
        "road_length": 3,
        "longest_road": false,
        "largest_army": true,
        "port_3_to_1": false,
        "ports_2_to_1": []
      },
      "winner_metrics": {
        "vp": 7.0,
        "public_vp": 6,
        "hidden_vp": 1.0,
        "building_vp": 4,
        "award_vp": 2,
        "cards": 4,
        "dev_cards_held": 2,
        "knights_played": 3,
        "settlements": 2,
        "cities": 1,
        "roads": 3,
        "road_length": 3,
        "longest_road": false,
        "largest_army": true,
        "port_3_to_1": false,
        "ports_2_to_1": []
      },
      "players": [
        {
          "vp": 3.0,
          "public_vp": 2,
          "hidden_vp": 1.0,
          "building_vp": 2,
          "award_vp": 0,
          "cards": 6,
          "dev_cards_held": 1,
          "knights_played": 2,
          "settlements": 2,
          "cities": 0,
          "roads": 4,
          "road_length": 4,
          "longest_road": false,
          "largest_army": false,
          "port_3_to_1": false,
          "ports_2_to_1": []
        },
        {
          "vp": 2.0,
          "public_vp": 2,
          "hidden_vp": 0.0,
          "building_vp": 2,
          "award_vp": 0,
          "cards": 9,
          "dev_cards_held": 0,
          "knights_played": 0,
          "settlements": 2,
          "cities": 0,
          "roads": 5,
          "road_length": 4,
          "longest_road": false,
          "largest_army": false,
          "port_3_to_1": false,
          "ports_2_to_1": []
        },
        {
          "vp": 4.0,
          "public_vp": 4,
          "hidden_vp": 0.0,
          "building_vp": 2,
          "award_vp": 2,
          "cards": 2,
          "dev_cards_held": 0,
          "knights_played": 0,
          "settlements": 2,
          "cities": 0,
          "roads": 15,
          "road_length": 9,
          "longest_road": true,
          "largest_army": false,
          "port_3_to_1": false,
          "ports_2_to_1": []
        },
        {
          "vp": 7.0,
          "public_vp": 6,
          "hidden_vp": 1.0,
          "building_vp": 4,
          "award_vp": 2,
          "cards": 4,
          "dev_cards_held": 2,
          "knights_played": 3,
          "settlements": 2,
          "cities": 1,
          "roads": 3,
          "road_length": 3,
          "longest_road": false,
          "largest_army": true,
          "port_3_to_1": false,
          "ports_2_to_1": []
        }
      ]
    },
    {
      "game": 12,
      "board_seed": 50200003,
      "candidate_seat": 0,
      "winner": 0,
      "won": true,
      "turns": 28,
      "vp_margin": 4.0,
      "opening": {
        "vertices": [
          14,
          25
        ],
        "income": [
          0.277778,
          0.0,
          0.222222,
          0.222222,
          0.0
        ],
        "income_by_resource": {
          "wheat": 0.277778,
          "sheep": 0.0,
          "wood": 0.222222,
          "brick": 0.222222,
          "stone": 0.0
        },
        "resource_diversity": 3,
        "strategy": {
          "expansion": 0.0,
          "city": 0.0,
          "development": 0.0,
          "best": 0.0
        }
      },
      "candidate_actions": {
        "settlement": 3,
        "road": 5,
        "end_turn": 4,
        "propose_trade": 17,
        "discard": 4,
        "confirm_trade": 5,
        "buy_dev": 1,
        "bank_trade": 1,
        "city": 1
      },
      "candidate": {
        "vp": 7.0,
        "public_vp": 6,
        "hidden_vp": 1.0,
        "building_vp": 4,
        "award_vp": 2,
        "cards": 3,
        "dev_cards_held": 1,
        "knights_played": 0,
        "settlements": 2,
        "cities": 1,
        "roads": 5,
        "road_length": 5,
        "longest_road": true,
        "largest_army": false,
        "port_3_to_1": false,
        "ports_2_to_1": []
      },
      "winner_metrics": {
        "vp": 7.0,
        "public_vp": 6,
        "hidden_vp": 1.0,
        "building_vp": 4,
        "award_vp": 2,
        "cards": 3,
        "dev_cards_held": 1,
        "knights_played": 0,
        "settlements": 2,
        "cities": 1,
        "roads": 5,
        "road_length": 5,
        "longest_road": true,
        "largest_army": false,
        "port_3_to_1": false,
        "ports_2_to_1": []
      },
      "players": [
        {
          "vp": 7.0,
          "public_vp": 6,
          "hidden_vp": 1.0,
          "building_vp": 4,
          "award_vp": 2,
          "cards": 3,
          "dev_cards_held": 1,
          "knights_played": 0,
          "settlements": 2,
          "cities": 1,
          "roads": 5,
          "road_length": 5,
          "longest_road": true,
          "largest_army": false,
          "port_3_to_1": false,
          "ports_2_to_1": []
        },
        {
          "vp": 3.0,
          "public_vp": 3,
          "hidden_vp": 0.0,
          "building_vp": 3,
          "award_vp": 0,
          "cards": 8,
          "dev_cards_held": 2,
          "knights_played": 0,
          "settlements": 1,
          "cities": 1,
          "roads": 3,
          "road_length": 3,
          "longest_road": false,
          "largest_army": false,
          "port_3_to_1": false,
          "ports_2_to_1": []
        },
        {
          "vp": 3.0,
          "public_vp": 3,
          "hidden_vp": 0.0,
          "building_vp": 3,
          "award_vp": 0,
          "cards": 7,
          "dev_cards_held": 0,
          "knights_played": 0,
          "settlements": 1,
          "cities": 1,
          "roads": 3,
          "road_length": 3,
          "longest_road": false,
          "largest_army": false,
          "port_3_to_1": false,
          "ports_2_to_1": []
        },
        {
          "vp": 2.0,
          "public_vp": 2,
          "hidden_vp": 0.0,
          "building_vp": 2,
          "award_vp": 0,
          "cards": 4,
          "dev_cards_held": 0,
          "knights_played": 0,
          "settlements": 2,
          "cities": 0,
          "roads": 6,
          "road_length": 3,
          "longest_road": false,
          "largest_army": false,
          "port_3_to_1": false,
          "ports_2_to_1": []
        }
      ]
    },
    {
      "game": 13,
      "board_seed": 50200003,
      "candidate_seat": 1,
      "winner": 1,
      "won": true,
      "turns": 37,
      "vp_margin": 3.0,
      "opening": {
        "vertices": [
          42,
          26
        ],
        "income": [
          0.333333,
          0.083333,
          0.083333,
          0.0,
          0.0
        ],
        "income_by_resource": {
          "wheat": 0.333333,
          "sheep": 0.083333,
          "wood": 0.083333,
          "brick": 0.0,
          "stone": 0.0
        },
        "resource_diversity": 3,
        "strategy": {
          "expansion": 0.0,
          "city": 0.0,
          "development": 0.0,
          "best": 0.0
        }
      },
      "candidate_actions": {
        "settlement": 2,
        "road": 2,
        "propose_trade": 26,
        "confirm_trade": 14,
        "buy_dev": 6,
        "end_turn": 5,
        "city": 1,
        "robber": 3,
        "steal": 2,
        "knight": 3
      },
      "candidate": {
        "vp": 7.0,
        "public_vp": 5,
        "hidden_vp": 2.0,
        "building_vp": 3,
        "award_vp": 2,
        "cards": 8,
        "dev_cards_held": 3,
        "knights_played": 3,
        "settlements": 1,
        "cities": 1,
        "roads": 2,
        "road_length": 2,
        "longest_road": false,
        "largest_army": true,
        "port_3_to_1": false,
        "ports_2_to_1": []
      },
      "winner_metrics": {
        "vp": 7.0,
        "public_vp": 5,
        "hidden_vp": 2.0,
        "building_vp": 3,
        "award_vp": 2,
        "cards": 8,
        "dev_cards_held": 3,
        "knights_played": 3,
        "settlements": 1,
        "cities": 1,
        "roads": 2,
        "road_length": 2,
        "longest_road": false,
        "largest_army": true,
        "port_3_to_1": false,
        "ports_2_to_1": []
      },
      "players": [
        {
          "vp": 4.0,
          "public_vp": 4,
          "hidden_vp": 0.0,
          "building_vp": 2,
          "award_vp": 2,
          "cards": 6,
          "dev_cards_held": 1,
          "knights_played": 0,
          "settlements": 2,
          "cities": 0,
          "roads": 9,
          "road_length": 6,
          "longest_road": true,
          "largest_army": false,
          "port_3_to_1": false,
          "ports_2_to_1": []
        },
        {
          "vp": 7.0,
          "public_vp": 5,
          "hidden_vp": 2.0,
          "building_vp": 3,
          "award_vp": 2,
          "cards": 8,
          "dev_cards_held": 3,
          "knights_played": 3,
          "settlements": 1,
          "cities": 1,
          "roads": 2,
          "road_length": 2,
          "longest_road": false,
          "largest_army": true,
          "port_3_to_1": false,
          "ports_2_to_1": []
        },
        {
          "vp": 2.0,
          "public_vp": 2,
          "hidden_vp": 0.0,
          "building_vp": 2,
          "award_vp": 0,
          "cards": 2,
          "dev_cards_held": 0,
          "knights_played": 0,
          "settlements": 2,
          "cities": 0,
          "roads": 6,
          "road_length": 4,
          "longest_road": false,
          "largest_army": false,
          "port_3_to_1": false,
          "ports_2_to_1": []
        },
        {
          "vp": 3.0,
          "public_vp": 3,
          "hidden_vp": 0.0,
          "building_vp": 3,
          "award_vp": 0,
          "cards": 4,
          "dev_cards_held": 0,
          "knights_played": 0,
          "settlements": 3,
          "cities": 0,
          "roads": 5,
          "road_length": 3,
          "longest_road": false,
          "largest_army": false,
          "port_3_to_1": false,
          "ports_2_to_1": []
        }
      ]
    },
    {
      "game": 14,
      "board_seed": 50200003,
      "candidate_seat": 2,
      "winner": 2,
      "won": true,
      "turns": 38,
      "vp_margin": 2.0,
      "opening": {
        "vertices": [
          3,
          30
        ],
        "income": [
          0.277778,
          0.083333,
          0.111111,
          0.222222,
          0.0
        ],
        "income_by_resource": {
          "wheat": 0.277778,
          "sheep": 0.083333,
          "wood": 0.111111,
          "brick": 0.222222,
          "stone": 0.0
        },
        "resource_diversity": 4,
        "strategy": {
          "expansion": 0.055556,
          "city": 0.0,
          "development": 0.0,
          "best": 0.055556
        }
      },
      "candidate_actions": {
        "settlement": 5,
        "road": 6,
        "propose_trade": 27,
        "confirm_trade": 14,
        "end_turn": 2,
        "discard": 12,
        "robber": 2,
        "steal": 2,
        "buy_dev": 2,
        "road_building": 1,
        "bank_trade": 1,
        "city": 1
      },
      "candidate": {
        "vp": 7.0,
        "public_vp": 6,
        "hidden_vp": 1.0,
        "building_vp": 6,
        "award_vp": 0,
        "cards": 6,
        "dev_cards_held": 1,
        "knights_played": 0,
        "settlements": 4,
        "cities": 1,
        "roads": 6,
        "road_length": 4,
        "longest_road": false,
        "largest_army": false,
        "port_3_to_1": true,
        "ports_2_to_1": []
      },
      "winner_metrics": {
        "vp": 7.0,
        "public_vp": 6,
        "hidden_vp": 1.0,
        "building_vp": 6,
        "award_vp": 0,
        "cards": 6,
        "dev_cards_held": 1,
        "knights_played": 0,
        "settlements": 4,
        "cities": 1,
        "roads": 6,
        "road_length": 4,
        "longest_road": false,
        "largest_army": false,
        "port_3_to_1": true,
        "ports_2_to_1": []
      },
      "players": [
        {
          "vp": 5.0,
          "public_vp": 5,
          "hidden_vp": 0.0,
          "building_vp": 3,
          "award_vp": 2,
          "cards": 9,
          "dev_cards_held": 0,
          "knights_played": 2,
          "settlements": 1,
          "cities": 1,
          "roads": 10,
          "road_length": 9,
          "longest_road": true,
          "largest_army": false,
          "port_3_to_1": false,
          "ports_2_to_1": []
        },
        {
          "vp": 2.0,
          "public_vp": 2,
          "hidden_vp": 0.0,
          "building_vp": 2,
          "award_vp": 0,
          "cards": 7,
          "dev_cards_held": 0,
          "knights_played": 1,
          "settlements": 2,
          "cities": 0,
          "roads": 7,
          "road_length": 7,
          "longest_road": false,
          "largest_army": false,
          "port_3_to_1": false,
          "ports_2_to_1": []
        },
        {
          "vp": 7.0,
          "public_vp": 6,
          "hidden_vp": 1.0,
          "building_vp": 6,
          "award_vp": 0,
          "cards": 6,
          "dev_cards_held": 1,
          "knights_played": 0,
          "settlements": 4,
          "cities": 1,
          "roads": 6,
          "road_length": 4,
          "longest_road": false,
          "largest_army": false,
          "port_3_to_1": true,
          "ports_2_to_1": []
        },
        {
          "vp": 2.0,
          "public_vp": 2,
          "hidden_vp": 0.0,
          "building_vp": 2,
          "award_vp": 0,
          "cards": 6,
          "dev_cards_held": 0,
          "knights_played": 0,
          "settlements": 2,
          "cities": 0,
          "roads": 6,
          "road_length": 5,
          "longest_road": false,
          "largest_army": false,
          "port_3_to_1": false,
          "ports_2_to_1": []
        }
      ]
    },
    {
      "game": 15,
      "board_seed": 50200003,
      "candidate_seat": 3,
      "winner": 3,
      "won": true,
      "turns": 31,
      "vp_margin": 3.0,
      "opening": {
        "vertices": [
          18,
          30
        ],
        "income": [
          0.138889,
          0.083333,
          0.166667,
          0.138889,
          0.083333
        ],
        "income_by_resource": {
          "wheat": 0.138889,
          "sheep": 0.083333,
          "wood": 0.166667,
          "brick": 0.138889,
          "stone": 0.083333
        },
        "resource_diversity": 5,
        "strategy": {
          "expansion": 0.069445,
          "city": 0.027778,
          "development": 0.083333,
          "best": 0.083333
        }
      },
      "candidate_actions": {
        "settlement": 4,
        "road": 8,
        "propose_trade": 21,
        "confirm_trade": 16,
        "buy_dev": 2,
        "road_building": 2,
        "city": 1,
        "end_turn": 1
      },
      "candidate": {
        "vp": 7.0,
        "public_vp": 7,
        "hidden_vp": 0.0,
        "building_vp": 5,
        "award_vp": 2,
        "cards": 5,
        "dev_cards_held": 0,
        "knights_played": 0,
        "settlements": 3,
        "cities": 1,
        "roads": 8,
        "road_length": 8,
        "longest_road": true,
        "largest_army": false,
        "port_3_to_1": false,
        "ports_2_to_1": [
          "brick",
          "stone"
        ]
      },
      "winner_metrics": {
        "vp": 7.0,
        "public_vp": 7,
        "hidden_vp": 0.0,
        "building_vp": 5,
        "award_vp": 2,
        "cards": 5,
        "dev_cards_held": 0,
        "knights_played": 0,
        "settlements": 3,
        "cities": 1,
        "roads": 8,
        "road_length": 8,
        "longest_road": true,
        "largest_army": false,
        "port_3_to_1": false,
        "ports_2_to_1": [
          "brick",
          "stone"
        ]
      },
      "players": [
        {
          "vp": 3.0,
          "public_vp": 3,
          "hidden_vp": 0.0,
          "building_vp": 3,
          "award_vp": 0,
          "cards": 6,
          "dev_cards_held": 1,
          "knights_played": 1,
          "settlements": 3,
          "cities": 0,
          "roads": 3,
          "road_length": 3,
          "longest_road": false,
          "largest_army": false,
          "port_3_to_1": false,
          "ports_2_to_1": []
        },
        {
          "vp": 2.0,
          "public_vp": 2,
          "hidden_vp": 0.0,
          "building_vp": 2,
          "award_vp": 0,
          "cards": 5,
          "dev_cards_held": 0,
          "knights_played": 0,
          "settlements": 2,
          "cities": 0,
          "roads": 3,
          "road_length": 3,
          "longest_road": false,
          "largest_army": false,
          "port_3_to_1": false,
          "ports_2_to_1": []
        },
        {
          "vp": 4.0,
          "public_vp": 3,
          "hidden_vp": 1.0,
          "building_vp": 3,
          "award_vp": 0,
          "cards": 6,
          "dev_cards_held": 1,
          "knights_played": 0,
          "settlements": 1,
          "cities": 1,
          "roads": 3,
          "road_length": 3,
          "longest_road": false,
          "largest_army": false,
          "port_3_to_1": false,
          "ports_2_to_1": []
        },
        {
          "vp": 7.0,
          "public_vp": 7,
          "hidden_vp": 0.0,
          "building_vp": 5,
          "award_vp": 2,
          "cards": 5,
          "dev_cards_held": 0,
          "knights_played": 0,
          "settlements": 3,
          "cities": 1,
          "roads": 8,
          "road_length": 8,
          "longest_road": true,
          "largest_army": false,
          "port_3_to_1": false,
          "ports_2_to_1": [
            "brick",
            "stone"
          ]
        }
      ]
    }
  ]
}
